voxrow/__init__.py
voxrow/airflow.py
voxrow/geospatial.py
voxrow/query.py
voxrow/scrape.py
voxrow/extension/__init__.py
voxrow/extension/form.py
voxrow/extension/model.py
voxrow/extension/token.py
voxrow/extension/route/__init__.py
voxrow/extension/route/auth.py
voxrow/extension/route/database.py
voxrow/extension/route/error.py
voxrow/extension/route/user.py
voxrow/modify/__init__.py
voxrow/modify/flask.py
voxrow/modify/flask_wtf.py
voxrow/modify/flask_sqlalchemy/__init__.py
voxrow/modify/flask_sqlalchemy/model.py
voxrow/modify/flask_sqlalchemy/types.py
voxrow/server/Makefile
voxrow/server/docker-compose/letsencrypt.yml
voxrow/server/install/before.rules
voxrow/server/install/jail.local
voxrow/server/install/make_gnu.sh
voxrow/server/install/sshd_config
voxrow/server/install/sysctl.conf
voxrow/server/nginx/location.conf
voxrow/server/nginx/mime.types
voxrow/server/nginx/nginx.conf
voxrow/server/nginx/non_ssl.conf
voxrow/server/nginx/redirecting.conf
voxrow/server/nginx/ssl.conf
voxrow-0.9.37.dist-info/LICENSE
voxrow-0.9.37.dist-info/METADATA
voxrow-0.9.37.dist-info/WHEEL
voxrow-0.9.37.dist-info/top_level.txt
voxrow-0.9.37.dist-info/RECORD
