Metadata-Version: 2.1
Name: voxrow
Version: 0.9.37
Summary: VOXROW's library
Author-email: Pipin Fitriadi <pipinfitriadi@gmail.com>
License: MS-RSL
Project-URL: Repository, https://gitlab.com/voxrow/library
Keywords: voxrow,library,raw sql query,airflow,sqlalchemy
Classifier: Development Status :: 3 - Alpha
Classifier: Programming Language :: Python :: 3.8
Classifier: License :: Other/Proprietary License
Classifier: Operating System :: OS Independent
Classifier: Framework :: Apache Airflow
Classifier: Framework :: Flask
Classifier: Topic :: Database
Classifier: Topic :: Database :: Database Engines/Servers
Classifier: Topic :: Internet :: WWW/HTTP
Requires-Python: >=3.7.13
License-File: LICENSE
Provides-Extra: airflow
Requires-Dist: apache-airflow-providers-docker ==3.1.0 ; extra == 'airflow'
Requires-Dist: apache-airflow ==2.3.4 ; (python_version == "3.7.13") and extra == 'airflow'
Requires-Dist: apache-airflow ; (python_version > "3.7.13") and extra == 'airflow'
Provides-Extra: flask
Requires-Dist: flask-jwt-extended ; extra == 'flask'
Requires-Dist: Flask-SQLAlchemy ; extra == 'flask'
Requires-Dist: Flask-WTF ; extra == 'flask'
Provides-Extra: geospatial
Requires-Dist: requests ; extra == 'geospatial'
Provides-Extra: postgres
Requires-Dist: psycopg2-binary ; extra == 'postgres'
Provides-Extra: query
Requires-Dist: SQLAlchemy ==1.4.46 ; extra == 'query'
Requires-Dist: Jinja2 ; extra == 'query'
Requires-Dist: cryptography >=3.2.1 ; extra == 'query'
Requires-Dist: sshtunnel ; extra == 'query'
Provides-Extra: scrape
Requires-Dist: beautifulsoup4 ; extra == 'scrape'
Requires-Dist: cloudscraper ; extra == 'scrape'
Requires-Dist: selenium ; extra == 'scrape'
Requires-Dist: webdriver-manager ; extra == 'scrape'
